raphpy_distributions/Binomialdistribution.py
raphpy_distributions/Gaussiandistribution.py
raphpy_distributions/Generaldistribution.py
raphpy_distributions/__init__.py
raphpy_distributions-1.0.dist-info/METADATA
raphpy_distributions-1.0.dist-info/WHEEL
raphpy_distributions-1.0.dist-info/top_level.txt
raphpy_distributions-1.0.dist-info/RECORD
