Metadata-Version: 2.1
Name: raphpy-distributions
Version: 1.0
Summary: Gaussian distributions
Home-page: UNKNOWN
Author: Raphael Okeibunor
Author-email: UNKNOWN
License: UNKNOWN
Platform: UNKNOWN
Requires-Dist: matplotlib
